.gitignore
LICENSE
README.md
setup.py
tutorial.ipynb
tcrpeg/TCRpeg.py
tcrpeg/__init__.py
tcrpeg/classification.py
tcrpeg/evaluate.py
tcrpeg/model.py
tcrpeg/process_data.py
tcrpeg/utils.py
tcrpeg/word2vec.py
tcrpeg.egg-info/PKG-INFO
tcrpeg.egg-info/SOURCES.txt
tcrpeg.egg-info/dependency_links.txt
tcrpeg.egg-info/not-zip-safe
tcrpeg.egg-info/requires.txt
tcrpeg.egg-info/top_level.txt
tcrpeg/__pycache__/__init__.cpython-38.pyc
tcrpeg/data/TCRs_train.csv
tcrpeg/data/classification.csv
tcrpeg/data/embedding_32.txt
tcrpeg/data/pdf_test.csv
tcrpeg/figs/noise_experiment.jpg
tcrpeg/figs/sharing_curve.jpg
tcrpeg/figs/workflow.png
tcrpeg/figs/workflow_full.jpg
tcrpeg/scripts/classify.py
tcrpeg/scripts/evaluate.py
tcrpeg/scripts/generate.py
tcrpeg/scripts/train.py